linkml_dumper_utils/__init__.py
linkml_dumper_utils/common.py
linkml_dumper_utils/dataclass.py
linkml_dumper_utils/pydantic.py
linkml_dumper_utils-1.0.0.dist-info/licenses/LICENSE.txt
linkml_dumper_utils-1.0.0.dist-info/METADATA
linkml_dumper_utils-1.0.0.dist-info/WHEEL
linkml_dumper_utils-1.0.0.dist-info/top_level.txt
linkml_dumper_utils-1.0.0.dist-info/RECORD
