Metadata-Version: 2.4
Name: linkml-dumper-utils
Version: 1.0.0
Summary: Small attempt to make most linkml functionalities work with the generated pydantic models or dataclasses. In the future linkml might properly handle things and then this repo will become obsolete.
Author-email: "P. Schmurr" <philipp.schmurr@gmail.com>
Maintainer-email: "P. Schmurr" <philipp.schmurr@gmail.com>
License: MIT License
Keywords: linkml,pydantic,dumpers,dataclass,compat,format,conversion
Classifier: Development Status :: 3 - Alpha
Classifier: Framework :: Pydantic
Classifier: Intended Audience :: Developers
Classifier: Intended Audience :: Information Technology
Classifier: Intended Audience :: Science/Research
Classifier: Topic :: File Formats
Classifier: Topic :: File Formats :: JSON
Classifier: Topic :: File Formats :: JSON :: JSON Schema
Classifier: Topic :: Scientific/Engineering :: Information Analysis
Classifier: Topic :: Software Development
Classifier: Topic :: Software Development :: Code Generators
Classifier: License :: OSI Approved :: MIT License
Classifier: Programming Language :: Python :: 3
Classifier: Programming Language :: Python :: 3.12
Classifier: Programming Language :: Python :: 3.13
Classifier: Programming Language :: Python :: 3 :: Only
Requires-Python: >=3.12
License-File: LICENSE.txt
Requires-Dist: linkml-runtime<=1.9.5,>=1.8.0
Requires-Dist: pydantic<3.0.0,>=2.0.0
Provides-Extra: test
Requires-Dist: pytest; extra == "test"
Dynamic: license-file
